peaka/__init__.py
peaka/dbapi.py
peaka/sqlalchemy/__init__.py
peaka/sqlalchemy/dialect.py
peaka-1.1.0.dist-info/LICENSE
peaka-1.1.0.dist-info/METADATA
peaka-1.1.0.dist-info/WHEEL
peaka-1.1.0.dist-info/entry_points.txt
peaka-1.1.0.dist-info/top_level.txt
peaka-1.1.0.dist-info/RECORD
