Metadata-Version: 2.1
Name: peaka
Version: 1.1.0
Summary: A Python client for Peaka
Home-page: https://docs.peaka.com/db-drivers/python
Author: Peaka
Author-email: integrations@peaka.com
Keywords: data,peaka
Classifier: Development Status :: 5 - Production/Stable
Classifier: Intended Audience :: Developers
Classifier: Topic :: Software Development :: Build Tools
Classifier: License :: OSI Approved :: Apache Software License
Classifier: Operating System :: MacOS :: MacOS X
Classifier: Operating System :: POSIX
Classifier: Operating System :: Microsoft :: Windows
Classifier: Programming Language :: Python
Classifier: Programming Language :: Python :: 3
Classifier: Programming Language :: Python :: 3.8
Classifier: Programming Language :: Python :: 3.9
Classifier: Programming Language :: Python :: 3.10
Classifier: Programming Language :: Python :: 3.11
Classifier: Programming Language :: Python :: 3.12
Classifier: Programming Language :: Python :: Implementation :: CPython
Classifier: Programming Language :: Python :: Implementation :: PyPy
Classifier: Topic :: Database :: Front-Ends
Requires-Python: >=3.8
License-File: LICENSE
Requires-Dist: trino
Requires-Dist: SQLAlchemy
Provides-Extra: dev
Requires-Dist: check-manifest ; extra == 'dev'
Requires-Dist: pydoc-markdown ; extra == 'dev'
Requires-Dist: novella ; extra == 'dev'
Provides-Extra: test
Requires-Dist: coverage ; extra == 'test'
